{
  "name": "CDK Practice Dev Container",
  "image": "mcr.microsoft.com/vscode/devcontainers/typescript-node:0-14",
  "settings": {
    "terminal.integrated.shell.linux": "/bin/bash"
  },
  "extensions": [
    "ms-azuretools.vscode-docker",
    "dbaeumer.vscode-eslint"
  ],
  "postCreateCommand": "npm install",
  "remoteUser": "vscode",
  "workspaceMount": "source=${localWorkspaceFolder},target=/workspace,type=bind,consistency=cached",
  "workspaceFolder": "/workspace",
  "customizations": {
    "vscode": {
      "settings": {
        "files.exclude": {
          "**/project-A": false,
          "**/project-B": false
        }
      }
    }
  },
  "features": {
    "project-A": {
      "name": "Project A Dev Container",
      "config": "./project-A/.devcontainer/devcontainer.json"
    },
    "project-B": {
      "name": "Project B Dev Container",
      "config": "./project-B/.devcontainer/devcontainer.json"
    }
  }
}
